bardown_lib/__init__.py
bardown_lib/enums/__init__.py
bardown_lib/enums/grade.py
bardown_lib/enums/position.py
bardown_lib/enums/statistic_acronym.py
bardown_lib/errors/__init__.py
bardown_lib/errors/coaches_errors.py
bardown_lib/errors/games_errors.py
bardown_lib/errors/players_errors.py
bardown_lib/errors/statistics_errors.py
bardown_lib/errors/teams_errors.py
bardown_lib/models/__init__.py
bardown_lib/models/dao/__init__.py
bardown_lib/models/dao/coach.py
bardown_lib/models/dao/composite_game_statistics.py
bardown_lib/models/dao/composite_season_statistics.py
bardown_lib/models/dao/composite_statistics.py
bardown_lib/models/dao/composite_team.py
bardown_lib/models/dao/game.py
bardown_lib/models/dao/game_result.py
bardown_lib/models/dao/game_statistics.py
bardown_lib/models/dao/player.py
bardown_lib/models/dao/season_statistics.py
bardown_lib/models/dao/team.py
bardown_lib/models/dto/__init__.py
bardown_lib/models/dto/coach.py
bardown_lib/models/dto/composite_game_statistics.py
bardown_lib/models/dto/composite_season_statistics.py
bardown_lib/models/dto/composite_season_statistics_full.py
bardown_lib/models/dto/composite_statistics.py
bardown_lib/models/dto/composite_team.py
bardown_lib/models/dto/game.py
bardown_lib/models/dto/game_result.py
bardown_lib/models/dto/game_statistics.py
bardown_lib/models/dto/player.py
bardown_lib/models/dto/player_statistics.py
bardown_lib/models/dto/season_statistics.py
bardown_lib/models/dto/statistics.py
bardown_lib/models/dto/team copy.py
bardown_lib/models/dto/team.py
bardown_lib/models/dto/team_coach.py
bardown_lib/models/dto/team_player.py
bardown_lib/requests/__init__.py
bardown_lib/requests/coaches_request_filters.py
bardown_lib/requests/game_request_filters.py
bardown_lib/requests/ordering.py
bardown_lib/requests/pagination.py
bardown_lib/requests/player_data_service_request.py
bardown_lib/requests/players_filters.py
bardown_lib/requests/players_request_filters.py
bardown_lib/requests/statistics_request_filters.py
bardown_lib-0.1.4.dist-info/licenses/LICENSE
bardown_lib-0.1.4.dist-info/WHEEL
bardown_lib-0.1.4.dist-info/METADATA
bardown_lib-0.1.4.dist-info/RECORD
