Metadata-Version: 2.4
Name: bardown_lib
Version: 0.1.4
Summary: Library for Bardown application
Author: Zachary Foteff
Author-email: Zachary Foteff <zfoteff@protonmail.com>
License-Expression: MIT
License-File: LICENSE
Classifier: Programming Language :: Python :: 3
Classifier: Operating System :: OS Independent
Requires-Dist: annotated-types==0.7.0
Requires-Dist: pydantic==2.10.6
Requires-Dist: pydantic-core==2.27.2
Requires-Dist: typing-extensions==4.12.2
Maintainer: Zachary Foteff
Maintainer-email: Zachary Foteff <zfoteff@protonmail.com>
Requires-Python: >=3.11
Project-URL: Repository, https://github.com/zfoteff/bardown/tree/develop/src/bardown_lib
Project-URL: Issues, https://github.com/zfoteff/bardown/issues
